Metadata-Version: 2.1
Name: oneNeuron-pypi-5H1N0
Version: 0.0.2
Summary: Its a implementation of perceptron
Home-page: https://github.com/5H1N0/oneNeuron_pypi
Author: 5H1N0
Author-email: shinosamuel94@gmail.com
License: UNKNOWN
Project-URL: Bug Tracker, https://github.com/5H1N0/oneNeuron_pypi/issues
Platform: UNKNOWN
Classifier: Programming Language :: Python :: 3
Classifier: License :: OSI Approved :: MIT License
Classifier: Operating System :: OS Independent
Requires-Python: >=3.7
License-File: LICENSE
Requires-Dist: numpy
Requires-Dist: tqdm
